LICENSE
flask_botox/__init__.py
flask_botox-0.1.1.dist-info/LICENSE
flask_botox-0.1.1.dist-info/WHEEL
flask_botox-0.1.1.dist-info/METADATA
flask_botox-0.1.1.dist-info/RECORD
