Metadata-Version: 2.1
Name: flask-botox
Version: 0.1.1
Summary: Flask extension that ties boto3 clients and resources to the application context.
Home-page: https://github.com/jperras/flask-botox
License: MIT
Keywords: flask,boto3,aws
Author: Joel Perras
Author-email: joel@nerderati.com
Requires-Python: >=3.7,<4
Classifier: Environment :: Web Environment
Classifier: Intended Audience :: Developers
Classifier: License :: OSI Approved :: MIT License
Classifier: Operating System :: OS Independent
Classifier: Programming Language :: Python :: 3
Classifier: Programming Language :: Python :: 3.10
Classifier: Programming Language :: Python :: 3.7
Classifier: Programming Language :: Python :: 3.8
Classifier: Programming Language :: Python :: 3.9
Classifier: Topic :: Internet :: WWW/HTTP :: Dynamic Content
Classifier: Topic :: Software Development :: Libraries :: Python Modules
Requires-Dist: Flask (>=2.1.0,<3.0.0)
Requires-Dist: boto3 (>=1.24.49,<2.0.0)
Project-URL: Repository, https://github.com/jperras/flask-botox
